{
	"Type": "Card",
	"GUID": "ED326E7162D5723B098BFAD232D92FD1",
	"Name": "Secret Objectives (base 3/4)",
	"Metadata": "card.objective.secret:base/2",
	"CollisionType": "Regular",
	"Friction": 0.7,
	"Restitution": 0,
	"Density": 0.5,
	"SurfaceType": "Cardboard",
	"Roughness": 1,
	"Metallic": 0,
	"PrimaryColor": {
		"R": 255,
		"G": 255,
		"B": 255
	},
	"SecondaryColor": {
		"R": 0,
		"G": 0,
		"B": 0
	},
	"Flippable": true,
	"AutoStraighten": false,
	"ShouldSnap": true,
	"ScriptName": "",
	"Blueprint": "",
	"Models": [],
	"Collision": [],
	"Lights": [],
	"SnapPointsGlobal": false,
	"SnapPoints": [],
	"ZoomViewDirection": {
		"X": 0,
		"Y": 0,
		"Z": 0
	},
	"GroundAccessibility": "ZoomAndContext",
	"Tags": [],
	"FrontTexture": "locale/card/objective/secret/base/2.face.jpg",
	"BackTexture": "global/card/objective/secret.back.jpg",
	"HiddenTexture": "",
	"BackIndex": -2,
	"HiddenIndex": -3,
	"NumHorizontal": 3,
	"NumVertical": 2,
	"Width": 4.2,
	"Height": 6.3,
	"Thickness": 0.05,
	"HiddenInHand": true,
	"UsedWithCardHolders": true,
	"CanStack": true,
	"UsePrimaryColorForSide": false,
	"FrontTextureOverrideExposed": false,
	"AllowFlippedInStack": false,
	"MirrorBack": true,
	"Model": "Rounded",
	"Indices": [
		0,
		1,
		2,
		3,
		4,
		5
	],
	"CardNames": {
		"0": "Master the Laws of Physics",
		"1": "Mine Rare Minerals",
		"2": "Monopolize Production",
		"3": "Occupy the Seat of the Empire",
		"4": "Spark a Rebellion",
		"5": "Threaten Enemies"
	},
	"CardMetadata": {
		"0": "card.objective.secret:base/master_the_laws_of_physics",
		"1": "card.objective.secret:base/mine_rare_minerals",
		"2": "card.objective.secret:base/monopolize_production",
		"3": "card.objective.secret:base/occupy_the_seat_of_the_empire",
		"4": "card.objective.secret:base/spark_a_rebellion",
		"5": "card.objective.secret:base/threaten_enemies"
	},
	"CardTags": {}
}