{
	"Type": "Card",
	"GUID": "024556B153838044C356379E1A8503EB",
	"Name": "Agenda (pok)",
	"Metadata": "card.agenda:pok/0",
	"CollisionType": "Regular",
	"Friction": 0.7,
	"Restitution": 0,
	"Density": 0.5,
	"SurfaceType": "Cardboard",
	"Roughness": 1,
	"Metallic": 0,
	"PrimaryColor": {
		"R": 255,
		"G": 255,
		"B": 255
	},
	"SecondaryColor": {
		"R": 0,
		"G": 0,
		"B": 0
	},
	"Flippable": true,
	"AutoStraighten": false,
	"ShouldSnap": true,
	"ScriptName": "",
	"Blueprint": "",
	"Models": [],
	"Collision": [],
	"SnapPointsGlobal": false,
	"SnapPoints": [],
	"ZoomViewDirection": {
		"X": 0,
		"Y": 0,
		"Z": 0
	},
	"FrontTexture": "locale\\card\\agenda\\pok\\0.face.jpg",
	"BackTexture": "global\\card\\agenda.back.jpg",
	"HiddenTexture": "",
	"BackIndex": -2,
	"HiddenIndex": -3,
	"NumHorizontal": 8,
	"NumVertical": 2,
	"Width": 4.2,
	"Height": 6.3,
	"Thickness": 0.05,
	"HiddenInHand": true,
	"UsedWithCardHolders": true,
	"CanStack": true,
	"UsePrimaryColorForSide": false,
	"FrontTextureOverrideExposed": false,
	"AllowFlippedInStack": false,
	"MirrorBack": true,
	"Model": "Rounded",
	"Indices": [
		0,
		1,
		2,
		3,
		4,
		5,
		6,
		7,
		8,
		9,
		10,
		11,
		12
	],
	"CardNames": {
		"0": "Armed Forces Standardization",
		"1": "Articles of War",
		"2": "Checks and Balances",
		"3": "Clandestine Operations",
		"4": "Covert Legislation",
		"5": "Galactic Crisis Pact",
		"6": "Minister of Antiquities",
		"7": "Nexus Sovereignty",
		"8": "Political Censure",
		"9": "Rearmament Agreement",
		"10": "Representative Government",
		"11": "Research Grant Reallocation",
		"12": "Search Warrant"
	},
	"CardMetadata": {
		"0": "card.agenda:pok/armed_forces_standardization",
		"1": "card.agenda:pok/articles_of_war",
		"2": "card.agenda:pok/checks_and_balances",
		"3": "card.agenda:pok/clandestine_operations",
		"4": "card.agenda:pok/covert_legislation",
		"5": "card.agenda:pok/galactic_crisis_pact",
		"6": "card.agenda:pok/minister_of_antiquities",
		"7": "card.agenda:pok/nexus_sovereignty",
		"8": "card.agenda:pok/political_censure",
		"9": "card.agenda:pok/rearmament_agreement",
		"10": "card.agenda:pok/representative_government",
		"11": "card.agenda:pok/research_grant_reallocation",
		"12": "card.agenda:pok/search_warrant"
	}
}